yardi_sdk/__init__.py
yardi_sdk/core.py
yardi_sdk/py.typed
yardi_sdk/utils.py
yardi_sdk/endpoints/__init__.py
yardi_sdk/endpoints/billing_and_payments.py
yardi_sdk/endpoints/common_data.py
yardi_sdk/endpoints/service_requests.py
yardi_sdk/endpoints/vendor_invoicing.py
yardi_sdk-0.1.11.dist-info/METADATA
yardi_sdk-0.1.11.dist-info/WHEEL
yardi_sdk-0.1.11.dist-info/licenses/LICENSE
yardi_sdk-0.1.11.dist-info/RECORD
