Metadata-Version: 2.4
Name: yardi-sdk
Version: 0.1.11
Summary: Yardi SDK for Python
Project-URL: Repository, https://github.com/yhavin/yardi-sdk
Author-email: yhavin <y.havin@gmail.com>
License-File: LICENSE
Keywords: api,management,property,real estate,sdk,yardi
Classifier: License :: OSI Approved :: MIT License
Classifier: Programming Language :: Python :: 3
Requires-Python: >=3.12
Requires-Dist: lxml>=5.3.0
Requires-Dist: python-dotenv>=1.0.1
Requires-Dist: requests>=2.32.3
Requires-Dist: zeep>=4.3.1
